lxmlrpc_monkey.py
lxmlrpc_monkey-1.0.0.dist-info/metadata.json
lxmlrpc_monkey-1.0.0.dist-info/RECORD
lxmlrpc_monkey-1.0.0.dist-info/DESCRIPTION.rst
lxmlrpc_monkey-1.0.0.dist-info/METADATA
lxmlrpc_monkey-1.0.0.dist-info/top_level.txt
lxmlrpc_monkey-1.0.0.dist-info/WHEEL
