Metadata-Version: 2.0
Name: lxmlrpc-monkey
Version: 1.0.0
Summary: xmlrpclib patch to reduce its memory consumption
Home-page: https://github.com/katyukha/lxmlrpc_monkey
Author: Dmytro Katyukha
Author-email: firemage.dima@gmail.com
License: GPL
Keywords: xmlrpc,xmlrpclib
Platform: UNKNOWN
Classifier: Development Status :: 4 - Beta
Classifier: Intended Audience :: Developers
Classifier: License :: OSI Approved :: GNU General Public License (GPL)
Classifier: License :: OSI Approved :: GNU General Public License v3 or later (GPLv3+)
Classifier: Programming Language :: Python :: 2.7
Classifier: Topic :: Software Development :: Libraries
Classifier: Topic :: Software Development :: Libraries :: Python Modules
Requires-Dist: lxml
